{
  "dash_id": "0b6c9e1e839d",
  "created_ts": "2026-02-13T05:04:56Z",
  "season_id": "3ea2b318-423b-cf86-25da-7cbb0eefbe2d",
  "team_a_key": "USC_Cardinal-Zzz_RS5-USC_Zundga_0824-ondoerae_love-Axio_1658-NUT_rodney_moon-shadowgoober1_thorn-khoyster_freak",
  "team_b_key": "BCIT_Black-balakeh_shhhh-shysoup_bruhf-Oomerz_oom-goblin_eater_munch-Mathman1129_1129",
  "team_a_name": "USC Cardinal",
  "team_b_name": "BCIT Black",
  "A": {
    "team_key": "USC_Cardinal-Zzz_RS5-USC_Zundga_0824-ondoerae_love-Axio_1658-NUT_rodney_moon-shadowgoober1_thorn-khoyster_freak",
    "team_name": "USC Cardinal",
    "season_id": "3ea2b318-423b-cf86-25da-7cbb0eefbe2d",
    "roster": [
      "Zzz#RS5",
      "USC Zundga#0824",
      "ondoerae#love",
      "Axio#1658",
      "NUT rodney#moon",
      "shadowgoober1#thorn",
      "khoyster#freak"
    ],
    "available_maps": [
      "Abyss",
      "Bind",
      "Breeze",
      "Corrode",
      "Haven",
      "Pearl",
      "Split"
    ],
    "map_rows": [
      {
        "map": "Pearl",
        "games": 82,
        "wins": 47,
        "losses": 35,
        "win_rate_pct": 57.3170731707317,
        "kd": 1.048048780487805,
        "kill_round": 1.0947560975609756,
        "dmg_round": 139.52439024390245,
        "score_round": 320.0731707317073
      },
      {
        "map": "Corrode",
        "games": 82,
        "wins": 43,
        "losses": 39,
        "win_rate_pct": 52.4390243902439,
        "kd": 1.079512195121951,
        "kill_round": 0.7951219512195122,
        "dmg_round": 145.4268292682927,
        "score_round": 224.8170731707317
      },
      {
        "map": "Split",
        "games": 77,
        "wins": 40,
        "losses": 37,
        "win_rate_pct": 51.94805194805194,
        "kd": 1.0323376623376623,
        "kill_round": 0.7711688311688313,
        "dmg_round": 142.6103896103896,
        "score_round": 221.58441558441558
      },
      {
        "map": "Bind",
        "games": 73,
        "wins": 33,
        "losses": 40,
        "win_rate_pct": 45.20547945205479,
        "kd": 1.0568493150684932,
        "kill_round": 0.8078082191780822,
        "dmg_round": 146.68493150684932,
        "score_round": 228.02739726027397
      },
      {
        "map": "Breeze",
        "games": 68,
        "wins": 41,
        "losses": 27,
        "win_rate_pct": 60.29411764705882,
        "kd": 1.1583823529411763,
        "kill_round": 0.7983823529411765,
        "dmg_round": 145.14705882352942,
        "score_round": 222.33823529411765
      },
      {
        "map": "Abyss",
        "games": 68,
        "wins": 30,
        "losses": 38,
        "win_rate_pct": 44.11764705882353,
        "kd": 1.0089705882352942,
        "kill_round": 0.7523529411764707,
        "dmg_round": 137.97058823529412,
        "score_round": 213.75
      },
      {
        "map": "Haven",
        "games": 67,
        "wins": 41,
        "losses": 26,
        "win_rate_pct": 61.19402985074627,
        "kd": 1.056268656716418,
        "kill_round": 0.8165671641791044,
        "dmg_round": 150.11940298507463,
        "score_round": 230.46268656716418
      }
    ],
    "players": [
      {
        "riot_id": "Zzz#RS5",
        "games": 219,
        "custom_games": 0,
        "win_rate_pct": 50.68493150684932,
        "kd": 1.03,
        "kill_round": 0.7800913242009132,
        "dmg_round": 142.11872146118722,
        "score_round": 220.1552511415525,
        "impact_index": 1223.0584898421357
      },
      {
        "riot_id": "khoyster#freak",
        "games": 119,
        "custom_games": 0,
        "win_rate_pct": 56.30252100840336,
        "kd": 1.0058823529411764,
        "kill_round": 0.802436974789916,
        "dmg_round": 145.63025210084032,
        "score_round": 232.00840336134453,
        "impact_index": 1117.2720701446508
      },
      {
        "riot_id": "Axio#1658",
        "games": 109,
        "custom_games": 0,
        "win_rate_pct": 57.798165137614674,
        "kd": 1.15697247706422,
        "kill_round": 0.7948623853211011,
        "dmg_round": 146.27522935779817,
        "score_round": 221.39449541284404,
        "impact_index": 1204.0155319199332
      },
      {
        "riot_id": "NUT rodney#moon",
        "games": 35,
        "custom_games": 0,
        "win_rate_pct": 48.57142857142857,
        "kd": 1.1725714285714286,
        "kill_round": 0.8217142857142856,
        "dmg_round": 147.9142857142857,
        "score_round": 230.71428571428572,
        "impact_index": 969.4457217685534
      },
      {
        "riot_id": "USC Zundga#0824",
        "games": 30,
        "custom_games": 0,
        "win_rate_pct": 50.0,
        "kd": 1.032,
        "kill_round": 0.7176666666666667,
        "dmg_round": 139.53333333333333,
        "score_round": 203.63333333333333,
        "impact_index": 721.6510374276717
      },
      {
        "riot_id": "ondoerae#love",
        "games": 4,
        "custom_games": 0,
        "win_rate_pct": 50.0,
        "kd": 1.0925,
        "kill_round": 0.8049999999999999,
        "dmg_round": 151.0,
        "score_round": 233.0,
        "impact_index": 409.68644420488135
      },
      {
        "riot_id": "shadowgoober1#thorn",
        "games": 1,
        "custom_games": 0,
        "win_rate_pct": 0.0,
        "kd": 1.5,
        "kill_round": 27.0,
        "dmg_round": 0.0,
        "score_round": 8413.0,
        "impact_index": 8747.170845076229
      }
    ],
    "agents": [
      {
        "agent": "Clove",
        "matches": 105,
        "win_rate": 53.923809523809524,
        "acs": 151.40952380952382,
        "dmg_round": 239.11428571428573
      },
      {
        "agent": "Chamber",
        "matches": 75,
        "win_rate": 53.17333333333333,
        "acs": 150.21333333333334,
        "dmg_round": 229.4
      },
      {
        "agent": "Sova",
        "matches": 73,
        "win_rate": 60.04109589041096,
        "acs": 137.53424657534248,
        "dmg_round": 202.04109589041096
      },
      {
        "agent": "Jett",
        "matches": 44,
        "win_rate": 52.68181818181818,
        "acs": 152.3409090909091,
        "dmg_round": 237.04545454545453
      },
      {
        "agent": "Reyna",
        "matches": 43,
        "win_rate": 60.627906976744185,
        "acs": 152.74418604651163,
        "dmg_round": 232.34883720930233
      },
      {
        "agent": "Fade",
        "matches": 34,
        "win_rate": 46.970588235294116,
        "acs": 127.82352941176471,
        "dmg_round": 202.47058823529412
      },
      {
        "agent": "Waylay",
        "matches": 30,
        "win_rate": 53.333333333333336,
        "acs": 131.5,
        "dmg_round": 210.86666666666667
      },
      {
        "agent": "Yoru",
        "matches": 26,
        "win_rate": 46.07692307692308,
        "acs": 143.96153846153845,
        "dmg_round": 224.6153846153846
      },
      {
        "agent": "Skye",
        "matches": 25,
        "win_rate": 44.04,
        "acs": 115.0,
        "dmg_round": 514.72
      },
      {
        "agent": "Raze",
        "matches": 21,
        "win_rate": 47.523809523809526,
        "acs": 152.0,
        "dmg_round": 238.04761904761904
      },
      {
        "agent": "Viper",
        "matches": 14,
        "win_rate": 56.857142857142854,
        "acs": 142.07142857142858,
        "dmg_round": 217.35714285714286
      },
      {
        "agent": "Astra",
        "matches": 8,
        "win_rate": 37.75,
        "acs": 121.25,
        "dmg_round": 197.5
      },
      {
        "agent": "Neon",
        "matches": 4,
        "win_rate": 50.0,
        "acs": 127.0,
        "dmg_round": 206.0
      },
      {
        "agent": "Tejo",
        "matches": 4,
        "win_rate": 100.0,
        "acs": 164.25,
        "dmg_round": 244.25
      },
      {
        "agent": "Veto",
        "matches": 3,
        "win_rate": 0.0,
        "acs": 114.33333333333333,
        "dmg_round": 184.33333333333334
      },
      {
        "agent": "Cypher",
        "matches": 3,
        "win_rate": 0.0,
        "acs": 162.0,
        "dmg_round": 261.6666666666667
      },
      {
        "agent": "Vyse",
        "matches": 3,
        "win_rate": 67.0,
        "acs": 185.0,
        "dmg_round": 305.0
      },
      {
        "agent": "Sage",
        "matches": 2,
        "win_rate": 50.0,
        "acs": 186.0,
        "dmg_round": 293.0
      },
      {
        "agent": "Omen",
        "matches": 2,
        "win_rate": 0.0,
        "acs": 134.5,
        "dmg_round": 218.5
      },
      {
        "agent": "KAY/O",
        "matches": 1,
        "win_rate": 0.0,
        "acs": 110.0,
        "dmg_round": 163.0
      },
      {
        "agent": "Phoenix",
        "matches": 1,
        "win_rate": 0.0,
        "acs": 156.0,
        "dmg_round": 233.0
      }
    ],
    "summary": {
      "total_games": 517,
      "custom_games": 0,
      "custom_games_weight": 1.15,
      "avg_win_rate_pct": 53.191489361702125,
      "avg_kd": 1.0623791102514506,
      "avg_dmg_round": 143.8394584139265,
      "avg_score_round": 238.84719535783367,
      "stable_map_count": 7,
      "win_volatility": 6.321475395757903,
      "best_map": {
        "map": "Haven",
        "games": 67,
        "wins": 41,
        "losses": 26,
        "win_rate_pct": 61.19402985074627,
        "kd": 1.056268656716418,
        "kill_round": 0.8165671641791044,
        "dmg_round": 150.11940298507463,
        "score_round": 230.46268656716418
      },
      "worst_map": {
        "map": "Abyss",
        "games": 68,
        "wins": 30,
        "losses": 38,
        "win_rate_pct": 44.11764705882353,
        "kd": 1.0089705882352942,
        "kill_round": 0.7523529411764707,
        "dmg_round": 137.97058823529412,
        "score_round": 213.75
      },
      "top_agent": {
        "agent": "Clove",
        "matches": 105,
        "win_rate": 53.923809523809524,
        "acs": 151.40952380952382,
        "dmg_round": 239.11428571428573
      }
    },
    "top_impact_players": [
      {
        "riot_id": "shadowgoober1#thorn",
        "games": 1,
        "custom_games": 0,
        "win_rate_pct": 0.0,
        "kd": 1.5,
        "kill_round": 27.0,
        "dmg_round": 0.0,
        "score_round": 8413.0,
        "impact_index": 8747.170845076229
      },
      {
        "riot_id": "Zzz#RS5",
        "games": 219,
        "custom_games": 0,
        "win_rate_pct": 50.68493150684932,
        "kd": 1.03,
        "kill_round": 0.7800913242009132,
        "dmg_round": 142.11872146118722,
        "score_round": 220.1552511415525,
        "impact_index": 1223.0584898421357
      },
      {
        "riot_id": "Axio#1658",
        "games": 109,
        "custom_games": 0,
        "win_rate_pct": 57.798165137614674,
        "kd": 1.15697247706422,
        "kill_round": 0.7948623853211011,
        "dmg_round": 146.27522935779817,
        "score_round": 221.39449541284404,
        "impact_index": 1204.0155319199332
      }
    ],
    "top_agents": [
      {
        "agent": "Clove",
        "matches": 105,
        "win_rate": 53.923809523809524,
        "acs": 151.40952380952382,
        "dmg_round": 239.11428571428573
      },
      {
        "agent": "Chamber",
        "matches": 75,
        "win_rate": 53.17333333333333,
        "acs": 150.21333333333334,
        "dmg_round": 229.4
      },
      {
        "agent": "Sova",
        "matches": 73,
        "win_rate": 60.04109589041096,
        "acs": 137.53424657534248,
        "dmg_round": 202.04109589041096
      },
      {
        "agent": "Jett",
        "matches": 44,
        "win_rate": 52.68181818181818,
        "acs": 152.3409090909091,
        "dmg_round": 237.04545454545453
      },
      {
        "agent": "Reyna",
        "matches": 43,
        "win_rate": 60.627906976744185,
        "acs": 152.74418604651163,
        "dmg_round": 232.34883720930233
      }
    ],
    "role_balance": {
      "Initiator": 133,
      "Duelist": 169,
      "Controller": 129,
      "Sentinel": 83,
      "Unknown": 7
    },
    "map_plan": {
      "pick_targets": [
        {
          "map": "Haven",
          "games": 67,
          "wins": 41,
          "losses": 26,
          "win_rate_pct": 61.19402985074627,
          "adj_win_rate_pct": 60.273972602739725,
          "confidence": "High",
          "confidence_class": "pill-good"
        },
        {
          "map": "Breeze",
          "games": 68,
          "wins": 41,
          "losses": 27,
          "win_rate_pct": 60.29411764705882,
          "adj_win_rate_pct": 59.45945945945946,
          "confidence": "High",
          "confidence_class": "pill-good"
        },
        {
          "map": "Pearl",
          "games": 82,
          "wins": 47,
          "losses": 35,
          "win_rate_pct": 57.3170731707317,
          "adj_win_rate_pct": 56.81818181818182,
          "confidence": "High",
          "confidence_class": "pill-good"
        }
      ],
      "ban_targets": [
        {
          "map": "Abyss",
          "games": 68,
          "wins": 30,
          "losses": 38,
          "win_rate_pct": 44.11764705882353,
          "adj_win_rate_pct": 44.5945945945946,
          "confidence": "High",
          "confidence_class": "pill-good"
        },
        {
          "map": "Bind",
          "games": 73,
          "wins": 33,
          "losses": 40,
          "win_rate_pct": 45.20547945205479,
          "adj_win_rate_pct": 45.56962025316456,
          "confidence": "High",
          "confidence_class": "pill-good"
        },
        {
          "map": "Split",
          "games": 77,
          "wins": 40,
          "losses": 37,
          "win_rate_pct": 51.94805194805194,
          "adj_win_rate_pct": 51.80722891566265,
          "confidence": "High",
          "confidence_class": "pill-good"
        }
      ],
      "first_pick": {
        "map": "Haven",
        "games": 67,
        "wins": 41,
        "losses": 26,
        "win_rate_pct": 61.19402985074627,
        "adj_win_rate_pct": 60.273972602739725,
        "confidence": "High",
        "confidence_class": "pill-good"
      },
      "first_ban": {
        "map": "Abyss",
        "games": 68,
        "wins": 30,
        "losses": 38,
        "win_rate_pct": 44.11764705882353,
        "adj_win_rate_pct": 44.5945945945946,
        "confidence": "High",
        "confidence_class": "pill-good"
      }
    },
    "expected_comps": [
      {
        "map": "Pearl",
        "games": 82,
        "agents": [
          {
            "agent": "Sova",
            "role": "Initiator",
            "player": "Zzz#RS5",
            "matches": 39,
            "win_rate": 64.0,
            "conflict": false
          },
          {
            "agent": "Chamber",
            "role": "Sentinel",
            "player": "Axio#1658",
            "matches": 56,
            "win_rate": 55.0,
            "conflict": false
          },
          {
            "agent": "Clove",
            "role": "Controller",
            "player": "khoyster#freak",
            "matches": 69,
            "win_rate": 59.0,
            "conflict": false
          },
          {
            "agent": "Skye",
            "role": "Initiator",
            "player": "USC Zundga#0824",
            "matches": 4,
            "win_rate": 25.0,
            "conflict": false
          },
          {
            "agent": "Yoru",
            "role": "Duelist",
            "player": "NUT rodney#moon",
            "matches": 18,
            "win_rate": 50.0,
            "conflict": false
          }
        ],
        "roles_label": "1 Controller / 2 Initiator / 1 Sentinel / 1 Duelist",
        "confidence": "High",
        "confidence_class": "pill-good",
        "conflicts": 0
      },
      {
        "map": "Corrode",
        "games": 82,
        "agents": [
          {
            "agent": "Sova",
            "role": "Initiator",
            "player": "Zzz#RS5",
            "matches": 39,
            "win_rate": 64.0,
            "conflict": false
          },
          {
            "agent": "Chamber",
            "role": "Sentinel",
            "player": "Axio#1658",
            "matches": 56,
            "win_rate": 55.0,
            "conflict": false
          },
          {
            "agent": "Clove",
            "role": "Controller",
            "player": "khoyster#freak",
            "matches": 69,
            "win_rate": 59.0,
            "conflict": false
          },
          {
            "agent": "Yoru",
            "role": "Duelist",
            "player": "NUT rodney#moon",
            "matches": 18,
            "win_rate": 50.0,
            "conflict": false
          },
          {
            "agent": "Skye",
            "role": "Initiator",
            "player": "USC Zundga#0824",
            "matches": 4,
            "win_rate": 25.0,
            "conflict": false
          }
        ],
        "roles_label": "1 Controller / 2 Initiator / 1 Sentinel / 1 Duelist",
        "confidence": "High",
        "confidence_class": "pill-good",
        "conflicts": 0
      },
      {
        "map": "Split",
        "games": 77,
        "agents": [
          {
            "agent": "Sova",
            "role": "Initiator",
            "player": "Zzz#RS5",
            "matches": 39,
            "win_rate": 64.0,
            "conflict": false
          },
          {
            "agent": "Clove",
            "role": "Controller",
            "player": "khoyster#freak",
            "matches": 69,
            "win_rate": 59.0,
            "conflict": false
          },
          {
            "agent": "Chamber",
            "role": "Sentinel",
            "player": "Axio#1658",
            "matches": 56,
            "win_rate": 55.0,
            "conflict": false
          },
          {
            "agent": "Yoru",
            "role": "Duelist",
            "player": "NUT rodney#moon",
            "matches": 18,
            "win_rate": 50.0,
            "conflict": false
          },
          {
            "agent": "Skye",
            "role": "Initiator",
            "player": "USC Zundga#0824",
            "matches": 4,
            "win_rate": 25.0,
            "conflict": false
          }
        ],
        "roles_label": "1 Controller / 2 Initiator / 1 Sentinel / 1 Duelist",
        "confidence": "High",
        "confidence_class": "pill-good",
        "conflicts": 0
      },
      {
        "map": "Bind",
        "games": 73,
        "agents": [
          {
            "agent": "Sova",
            "role": "Initiator",
            "player": "Zzz#RS5",
            "matches": 39,
            "win_rate": 64.0,
            "conflict": false
          },
          {
            "agent": "Chamber",
            "role": "Sentinel",
            "player": "Axio#1658",
            "matches": 56,
            "win_rate": 55.0,
            "conflict": false
          },
          {
            "agent": "Clove",
            "role": "Controller",
            "player": "khoyster#freak",
            "matches": 69,
            "win_rate": 59.0,
            "conflict": false
          },
          {
            "agent": "Skye",
            "role": "Initiator",
            "player": "USC Zundga#0824",
            "matches": 4,
            "win_rate": 25.0,
            "conflict": false
          },
          {
            "agent": "Yoru",
            "role": "Duelist",
            "player": "NUT rodney#moon",
            "matches": 18,
            "win_rate": 50.0,
            "conflict": false
          }
        ],
        "roles_label": "1 Controller / 2 Initiator / 1 Sentinel / 1 Duelist",
        "confidence": "High",
        "confidence_class": "pill-good",
        "conflicts": 0
      },
      {
        "map": "Breeze",
        "games": 68,
        "agents": [
          {
            "agent": "Sova",
            "role": "Initiator",
            "player": "Zzz#RS5",
            "matches": 39,
            "win_rate": 64.0,
            "conflict": false
          },
          {
            "agent": "Clove",
            "role": "Controller",
            "player": "khoyster#freak",
            "matches": 69,
            "win_rate": 59.0,
            "conflict": false
          },
          {
            "agent": "Chamber",
            "role": "Sentinel",
            "player": "Axio#1658",
            "matches": 56,
            "win_rate": 55.0,
            "conflict": false
          },
          {
            "agent": "Yoru",
            "role": "Duelist",
            "player": "NUT rodney#moon",
            "matches": 18,
            "win_rate": 50.0,
            "conflict": false
          },
          {
            "agent": "Skye",
            "role": "Initiator",
            "player": "USC Zundga#0824",
            "matches": 4,
            "win_rate": 25.0,
            "conflict": false
          }
        ],
        "roles_label": "1 Controller / 2 Initiator / 1 Sentinel / 1 Duelist",
        "confidence": "High",
        "confidence_class": "pill-good",
        "conflicts": 0
      },
      {
        "map": "Abyss",
        "games": 68,
        "agents": [
          {
            "agent": "Sova",
            "role": "Initiator",
            "player": "Zzz#RS5",
            "matches": 39,
            "win_rate": 64.0,
            "conflict": false
          },
          {
            "agent": "Clove",
            "role": "Controller",
            "player": "khoyster#freak",
            "matches": 69,
            "win_rate": 59.0,
            "conflict": false
          },
          {
            "agent": "Chamber",
            "role": "Sentinel",
            "player": "Axio#1658",
            "matches": 56,
            "win_rate": 55.0,
            "conflict": false
          },
          {
            "agent": "Yoru",
            "role": "Duelist",
            "player": "NUT rodney#moon",
            "matches": 18,
            "win_rate": 50.0,
            "conflict": false
          },
          {
            "agent": "Skye",
            "role": "Initiator",
            "player": "USC Zundga#0824",
            "matches": 4,
            "win_rate": 25.0,
            "conflict": false
          }
        ],
        "roles_label": "1 Controller / 2 Initiator / 1 Sentinel / 1 Duelist",
        "confidence": "High",
        "confidence_class": "pill-good",
        "conflicts": 0
      },
      {
        "map": "Haven",
        "games": 67,
        "agents": [
          {
            "agent": "Sova",
            "role": "Initiator",
            "player": "Zzz#RS5",
            "matches": 39,
            "win_rate": 64.0,
            "conflict": false
          },
          {
            "agent": "Clove",
            "role": "Controller",
            "player": "khoyster#freak",
            "matches": 69,
            "win_rate": 59.0,
            "conflict": false
          },
          {
            "agent": "Chamber",
            "role": "Sentinel",
            "player": "Axio#1658",
            "matches": 56,
            "win_rate": 55.0,
            "conflict": false
          },
          {
            "agent": "Skye",
            "role": "Initiator",
            "player": "USC Zundga#0824",
            "matches": 4,
            "win_rate": 25.0,
            "conflict": false
          },
          {
            "agent": "Yoru",
            "role": "Duelist",
            "player": "NUT rodney#moon",
            "matches": 18,
            "win_rate": 50.0,
            "conflict": false
          }
        ],
        "roles_label": "1 Controller / 2 Initiator / 1 Sentinel / 1 Duelist",
        "confidence": "High",
        "confidence_class": "pill-good",
        "conflicts": 0
      }
    ],
    "team_insights": [
      {
        "level": "pill-good",
        "tag": "Sample",
        "text": "Solid sample size (517 games). Trends are more trustworthy."
      },
      {
        "level": "pill-good",
        "tag": "Map Pool",
        "text": "Wide map pool (7 maps with >=5 games)."
      },
      {
        "level": "pill-good",
        "tag": "Consistency",
        "text": "Stable across maps (win% stdev 6.3)."
      },
      {
        "level": "pill-mid",
        "tag": "Map Gap",
        "text": "Noticeable map gap: Haven 61.2% vs Abyss 44.1%."
      },
      {
        "level": "pill-good",
        "tag": "Agent Pool",
        "text": "Healthy agent diversity (top 2 = 35% of matches)."
      },
      {
        "level": "pill-mid",
        "tag": "Reliance",
        "text": "Top-heavy impact (top 2 = 69% of team impact). Target carries."
      }
    ]
  },
  "B": {
    "team_key": "BCIT_Black-balakeh_shhhh-shysoup_bruhf-Oomerz_oom-goblin_eater_munch-Mathman1129_1129",
    "team_name": "BCIT Black",
    "season_id": "3ea2b318-423b-cf86-25da-7cbb0eefbe2d",
    "roster": [
      "balakeh#shhhh",
      "shysoup#bruhf",
      "Oomerz#oom",
      "goblin eater#munch",
      "Mathman1129#1129"
    ],
    "available_maps": [
      "Abyss",
      "Ascent",
      "Bind",
      "Breeze",
      "Corrode",
      "Haven",
      "Lotus",
      "Pearl",
      "Skirmish A",
      "Skirmish B",
      "Skirmish C",
      "Split",
      "Sunset"
    ],
    "map_rows": [
      {
        "map": "Corrode",
        "games": 35,
        "wins": 24,
        "losses": 11,
        "win_rate_pct": 68.57142857142857,
        "kd": 1.1761904761904762,
        "kill_round": 0.8188461538461538,
        "dmg_round": 143.9752380952381,
        "score_round": 223.31238095238095
      },
      {
        "map": "Haven",
        "games": 25,
        "wins": 8,
        "losses": 17,
        "win_rate_pct": 32.0,
        "kd": 1.0366666666666666,
        "kill_round": 0.7365217391304348,
        "dmg_round": 140.91733333333335,
        "score_round": 212.94133333333332
      },
      {
        "map": "Bind",
        "games": 25,
        "wins": 15,
        "losses": 10,
        "win_rate_pct": 60.0,
        "kd": 1.1344,
        "kill_round": 0.7866666666666666,
        "dmg_round": 144.592,
        "score_round": 219.592
      },
      {
        "map": "Breeze",
        "games": 20,
        "wins": 12,
        "losses": 8,
        "win_rate_pct": 60.0,
        "kd": 1.1285,
        "kill_round": 0.7736842105263159,
        "dmg_round": 143.12,
        "score_round": 213.0
      },
      {
        "map": "Abyss",
        "games": 20,
        "wins": 12,
        "losses": 8,
        "win_rate_pct": 60.0,
        "kd": 1.1963333333333332,
        "kill_round": 0.7938888888888889,
        "dmg_round": 144.48333333333332,
        "score_round": 217.06666666666666
      },
      {
        "map": "Pearl",
        "games": 19,
        "wins": 11,
        "losses": 8,
        "win_rate_pct": 57.89473684210527,
        "kd": 1.2284210526315789,
        "kill_round": 0.8431578947368421,
        "dmg_round": 158.0,
        "score_round": 241.05263157894737
      },
      {
        "map": "Split",
        "games": 17,
        "wins": 7,
        "losses": 10,
        "win_rate_pct": 41.17647058823529,
        "kd": 0.9821568627450982,
        "kill_round": 0.6938461538461538,
        "dmg_round": 138.33333333333331,
        "score_round": 206.9294117647059
      }
    ],
    "players": [
      {
        "riot_id": "goblin eater#munch",
        "games": 55,
        "custom_games": 21,
        "win_rate_pct": 56.14789337919175,
        "kd": 1.0104901117798795,
        "kill_round": 0.7664705882352941,
        "dmg_round": 128.41616509028376,
        "score_round": 197.48925193465178,
        "impact_index": 803.3029521900348
      },
      {
        "riot_id": "shysoup#bruhf",
        "games": 53,
        "custom_games": 11,
        "win_rate_pct": 62.30558096980786,
        "kd": 1.1227813357731016,
        "kill_round": 0.8147619047619047,
        "dmg_round": 144.42177493138152,
        "score_round": 218.01006404391583,
        "impact_index": 976.4140646925158
      },
      {
        "riot_id": "balakeh#shhhh",
        "games": 48,
        "custom_games": 19,
        "win_rate_pct": 50.14749262536874,
        "kd": 1.1345132743362831,
        "kill_round": 0.7355172413793104,
        "dmg_round": 143.91445427728613,
        "score_round": 215.63028515240904,
        "impact_index": 952.0770965177016
      },
      {
        "riot_id": "Oomerz#oom",
        "games": 37,
        "custom_games": 20,
        "win_rate_pct": 48.75,
        "kd": 1.051125,
        "kill_round": 0.7288235294117648,
        "dmg_round": 149.975,
        "score_round": 228.9975,
        "impact_index": 875.5851663462287
      },
      {
        "riot_id": "Mathman1129#1129",
        "games": 28,
        "custom_games": 11,
        "win_rate_pct": 60.87689713322091,
        "kd": 1.2483979763912312,
        "kill_round": 0.8694117647058823,
        "dmg_round": 140.75716694772345,
        "score_round": 217.70489038785834,
        "impact_index": 915.1715556714802
      }
    ],
    "agents": [
      {
        "agent": "Omen",
        "matches": 38,
        "win_rate": 60.473684210526315,
        "acs": 155.94736842105263,
        "dmg_round": 180.6315789473684
      },
      {
        "agent": "Viper",
        "matches": 23,
        "win_rate": 56.52173913043478,
        "acs": 199.65217391304347,
        "dmg_round": 159.2173913043478
      },
      {
        "agent": "Sova",
        "matches": 22,
        "win_rate": 59.27272727272727,
        "acs": 176.13636363636363,
        "dmg_round": 219.36363636363637
      },
      {
        "agent": "Yoru",
        "matches": 17,
        "win_rate": 41.1764705882353,
        "acs": 164.47058823529412,
        "dmg_round": 187.0
      },
      {
        "agent": "Vyse",
        "matches": 13,
        "win_rate": 76.76923076923077,
        "acs": 163.76923076923077,
        "dmg_round": 179.46153846153845
      },
      {
        "agent": "Skye",
        "matches": 12,
        "win_rate": 58.666666666666664,
        "acs": 147.83333333333334,
        "dmg_round": 207.0
      },
      {
        "agent": "Fade",
        "matches": 11,
        "win_rate": 72.72727272727273,
        "acs": 140.0,
        "dmg_round": 164.63636363636363
      },
      {
        "agent": "Raze",
        "matches": 11,
        "win_rate": 54.54545454545455,
        "acs": 233.0,
        "dmg_round": 202.45454545454547
      },
      {
        "agent": "Waylay",
        "matches": 10,
        "win_rate": 49.9,
        "acs": 217.5,
        "dmg_round": 181.0
      },
      {
        "agent": "Clove",
        "matches": 9,
        "win_rate": 55.55555555555556,
        "acs": 129.11111111111111,
        "dmg_round": 189.0
      },
      {
        "agent": "Chamber",
        "matches": 7,
        "win_rate": 14.285714285714286,
        "acs": 156.85714285714286,
        "dmg_round": 239.71428571428572
      },
      {
        "agent": "Astra",
        "matches": 7,
        "win_rate": 57.142857142857146,
        "acs": 158.42857142857142,
        "dmg_round": 214.42857142857142
      },
      {
        "agent": "Cypher",
        "matches": 6,
        "win_rate": 66.66666666666667,
        "acs": 132.66666666666666,
        "dmg_round": 200.16666666666666
      },
      {
        "agent": "Reyna",
        "matches": 6,
        "win_rate": 50.0,
        "acs": 175.0,
        "dmg_round": 265.0
      },
      {
        "agent": "Breach",
        "matches": 5,
        "win_rate": 39.8,
        "acs": 126.4,
        "dmg_round": 129.8
      },
      {
        "agent": "Brimstone",
        "matches": 5,
        "win_rate": 60.0,
        "acs": 149.4,
        "dmg_round": 135.0
      },
      {
        "agent": "Tejo",
        "matches": 4,
        "win_rate": 25.0,
        "acs": 119.5,
        "dmg_round": 173.0
      },
      {
        "agent": "Veto",
        "matches": 4,
        "win_rate": 50.0,
        "acs": 199.0,
        "dmg_round": 272.0
      },
      {
        "agent": "Jett",
        "matches": 4,
        "win_rate": 50.0,
        "acs": 208.25,
        "dmg_round": 214.5
      },
      {
        "agent": "Neon",
        "matches": 3,
        "win_rate": 66.66666666666667,
        "acs": 143.0,
        "dmg_round": 174.0
      },
      {
        "agent": "Phoenix",
        "matches": 2,
        "win_rate": 50.0,
        "acs": 161.0,
        "dmg_round": 231.0
      },
      {
        "agent": "Killjoy",
        "matches": 2,
        "win_rate": 50.0,
        "acs": 137.5,
        "dmg_round": 130.0
      },
      {
        "agent": "Sage",
        "matches": 1,
        "win_rate": 0.0,
        "acs": 117.0,
        "dmg_round": 86.0
      }
    ],
    "summary": {
      "total_games": 161,
      "custom_games": 22,
      "custom_games_weight": 1.15,
      "avg_win_rate_pct": 55.17346317711503,
      "avg_kd": 1.1274051531750864,
      "avg_dmg_round": 144.30852099817406,
      "avg_score_round": 218.97906269020086,
      "stable_map_count": 7,
      "win_volatility": 11.853588652126197,
      "best_map": {
        "map": "Corrode",
        "games": 35,
        "wins": 24,
        "losses": 11,
        "win_rate_pct": 68.57142857142857,
        "kd": 1.1761904761904762,
        "kill_round": 0.8188461538461538,
        "dmg_round": 143.9752380952381,
        "score_round": 223.31238095238095
      },
      "worst_map": {
        "map": "Haven",
        "games": 25,
        "wins": 8,
        "losses": 17,
        "win_rate_pct": 32.0,
        "kd": 1.0366666666666666,
        "kill_round": 0.7365217391304348,
        "dmg_round": 140.91733333333335,
        "score_round": 212.94133333333332
      },
      "top_agent": {
        "agent": "Omen",
        "matches": 38,
        "win_rate": 60.473684210526315,
        "acs": 155.94736842105263,
        "dmg_round": 180.6315789473684
      }
    },
    "top_impact_players": [
      {
        "riot_id": "shysoup#bruhf",
        "games": 53,
        "custom_games": 11,
        "win_rate_pct": 62.30558096980786,
        "kd": 1.1227813357731016,
        "kill_round": 0.8147619047619047,
        "dmg_round": 144.42177493138152,
        "score_round": 218.01006404391583,
        "impact_index": 976.4140646925158
      },
      {
        "riot_id": "balakeh#shhhh",
        "games": 48,
        "custom_games": 19,
        "win_rate_pct": 50.14749262536874,
        "kd": 1.1345132743362831,
        "kill_round": 0.7355172413793104,
        "dmg_round": 143.91445427728613,
        "score_round": 215.63028515240904,
        "impact_index": 952.0770965177016
      },
      {
        "riot_id": "Mathman1129#1129",
        "games": 28,
        "custom_games": 11,
        "win_rate_pct": 60.87689713322091,
        "kd": 1.2483979763912312,
        "kill_round": 0.8694117647058823,
        "dmg_round": 140.75716694772345,
        "score_round": 217.70489038785834,
        "impact_index": 915.1715556714802
      }
    ],
    "top_agents": [
      {
        "agent": "Omen",
        "matches": 38,
        "win_rate": 60.473684210526315,
        "acs": 155.94736842105263,
        "dmg_round": 180.6315789473684
      },
      {
        "agent": "Viper",
        "matches": 23,
        "win_rate": 56.52173913043478,
        "acs": 199.65217391304347,
        "dmg_round": 159.2173913043478
      },
      {
        "agent": "Sova",
        "matches": 22,
        "win_rate": 59.27272727272727,
        "acs": 176.13636363636363,
        "dmg_round": 219.36363636363637
      },
      {
        "agent": "Yoru",
        "matches": 17,
        "win_rate": 41.1764705882353,
        "acs": 164.47058823529412,
        "dmg_round": 187.0
      },
      {
        "agent": "Vyse",
        "matches": 13,
        "win_rate": 76.76923076923077,
        "acs": 163.76923076923077,
        "dmg_round": 179.46153846153845
      }
    ],
    "role_balance": {
      "Sentinel": 29,
      "Controller": 82,
      "Initiator": 50,
      "Unknown": 8,
      "Duelist": 53
    },
    "map_plan": {
      "pick_targets": [
        {
          "map": "Corrode",
          "games": 35,
          "wins": 24,
          "losses": 11,
          "win_rate_pct": 68.57142857142857,
          "adj_win_rate_pct": 65.85365853658537,
          "confidence": "High",
          "confidence_class": "pill-good"
        },
        {
          "map": "Bind",
          "games": 25,
          "wins": 15,
          "losses": 10,
          "win_rate_pct": 60.0,
          "adj_win_rate_pct": 58.06451612903226,
          "confidence": "High",
          "confidence_class": "pill-good"
        },
        {
          "map": "Breeze",
          "games": 20,
          "wins": 12,
          "losses": 8,
          "win_rate_pct": 60.0,
          "adj_win_rate_pct": 57.692307692307686,
          "confidence": "High",
          "confidence_class": "pill-good"
        }
      ],
      "ban_targets": [
        {
          "map": "Haven",
          "games": 25,
          "wins": 8,
          "losses": 17,
          "win_rate_pct": 32.0,
          "adj_win_rate_pct": 35.483870967741936,
          "confidence": "High",
          "confidence_class": "pill-good"
        },
        {
          "map": "Split",
          "games": 17,
          "wins": 7,
          "losses": 10,
          "win_rate_pct": 41.17647058823529,
          "adj_win_rate_pct": 43.47826086956522,
          "confidence": "High",
          "confidence_class": "pill-good"
        },
        {
          "map": "Pearl",
          "games": 19,
          "wins": 11,
          "losses": 8,
          "win_rate_pct": 57.89473684210527,
          "adj_win_rate_pct": 56.00000000000001,
          "confidence": "High",
          "confidence_class": "pill-good"
        }
      ],
      "first_pick": {
        "map": "Corrode",
        "games": 35,
        "wins": 24,
        "losses": 11,
        "win_rate_pct": 68.57142857142857,
        "adj_win_rate_pct": 65.85365853658537,
        "confidence": "High",
        "confidence_class": "pill-good"
      },
      "first_ban": {
        "map": "Haven",
        "games": 25,
        "wins": 8,
        "losses": 17,
        "win_rate_pct": 32.0,
        "adj_win_rate_pct": 35.483870967741936,
        "confidence": "High",
        "confidence_class": "pill-good"
      }
    },
    "expected_comps": [
      {
        "map": "Corrode",
        "games": 35,
        "agents": [
          {
            "agent": "Skye",
            "role": "Initiator",
            "player": "shysoup#bruhf",
            "matches": 8,
            "win_rate": 63.0,
            "conflict": false
          },
          {
            "agent": "Chamber",
            "role": "Sentinel",
            "player": "balakeh#shhhh",
            "matches": 5,
            "win_rate": 20.0,
            "conflict": false
          },
          {
            "agent": "Omen",
            "role": "Controller",
            "player": "goblin eater#munch",
            "matches": 14,
            "win_rate": 71.0,
            "conflict": false
          },
          {
            "agent": "Clove",
            "role": "Controller",
            "player": "Oomerz#oom",
            "matches": 5,
            "win_rate": 40.0,
            "conflict": false
          },
          {
            "agent": "Sova",
            "role": "Initiator",
            "player": "Mathman1129#1129",
            "matches": 6,
            "win_rate": 67.0,
            "conflict": false
          }
        ],
        "roles_label": "2 Controller / 2 Initiator / 1 Sentinel",
        "confidence": "High",
        "confidence_class": "pill-good",
        "conflicts": 0
      },
      {
        "map": "Haven",
        "games": 25,
        "agents": [
          {
            "agent": "Skye",
            "role": "Initiator",
            "player": "shysoup#bruhf",
            "matches": 8,
            "win_rate": 63.0,
            "conflict": false
          },
          {
            "agent": "Omen",
            "role": "Controller",
            "player": "goblin eater#munch",
            "matches": 14,
            "win_rate": 71.0,
            "conflict": false
          },
          {
            "agent": "Chamber",
            "role": "Sentinel",
            "player": "balakeh#shhhh",
            "matches": 5,
            "win_rate": 20.0,
            "conflict": false
          },
          {
            "agent": "Clove",
            "role": "Controller",
            "player": "Oomerz#oom",
            "matches": 5,
            "win_rate": 40.0,
            "conflict": false
          },
          {
            "agent": "Sova",
            "role": "Initiator",
            "player": "Mathman1129#1129",
            "matches": 6,
            "win_rate": 67.0,
            "conflict": false
          }
        ],
        "roles_label": "2 Controller / 2 Initiator / 1 Sentinel",
        "confidence": "High",
        "confidence_class": "pill-good",
        "conflicts": 0
      },
      {
        "map": "Bind",
        "games": 25,
        "agents": [
          {
            "agent": "Skye",
            "role": "Initiator",
            "player": "shysoup#bruhf",
            "matches": 8,
            "win_rate": 63.0,
            "conflict": false
          },
          {
            "agent": "Chamber",
            "role": "Sentinel",
            "player": "balakeh#shhhh",
            "matches": 5,
            "win_rate": 20.0,
            "conflict": false
          },
          {
            "agent": "Omen",
            "role": "Controller",
            "player": "goblin eater#munch",
            "matches": 14,
            "win_rate": 71.0,
            "conflict": false
          },
          {
            "agent": "Clove",
            "role": "Controller",
            "player": "Oomerz#oom",
            "matches": 5,
            "win_rate": 40.0,
            "conflict": false
          },
          {
            "agent": "Sova",
            "role": "Initiator",
            "player": "Mathman1129#1129",
            "matches": 6,
            "win_rate": 67.0,
            "conflict": false
          }
        ],
        "roles_label": "2 Controller / 2 Initiator / 1 Sentinel",
        "confidence": "High",
        "confidence_class": "pill-good",
        "conflicts": 0
      },
      {
        "map": "Breeze",
        "games": 20,
        "agents": [
          {
            "agent": "Skye",
            "role": "Initiator",
            "player": "shysoup#bruhf",
            "matches": 8,
            "win_rate": 63.0,
            "conflict": false
          },
          {
            "agent": "Chamber",
            "role": "Sentinel",
            "player": "balakeh#shhhh",
            "matches": 5,
            "win_rate": 20.0,
            "conflict": false
          },
          {
            "agent": "Omen",
            "role": "Controller",
            "player": "goblin eater#munch",
            "matches": 14,
            "win_rate": 71.0,
            "conflict": false
          },
          {
            "agent": "Sova",
            "role": "Initiator",
            "player": "Mathman1129#1129",
            "matches": 6,
            "win_rate": 67.0,
            "conflict": false
          }
        ],
        "roles_label": "1 Controller / 2 Initiator / 1 Sentinel",
        "confidence": "High",
        "confidence_class": "pill-good",
        "conflicts": 0
      },
      {
        "map": "Abyss",
        "games": 20,
        "agents": [
          {
            "agent": "Omen",
            "role": "Controller",
            "player": "goblin eater#munch",
            "matches": 14,
            "win_rate": 71.0,
            "conflict": false
          },
          {
            "agent": "Skye",
            "role": "Initiator",
            "player": "shysoup#bruhf",
            "matches": 8,
            "win_rate": 63.0,
            "conflict": false
          },
          {
            "agent": "Chamber",
            "role": "Sentinel",
            "player": "balakeh#shhhh",
            "matches": 5,
            "win_rate": 20.0,
            "conflict": false
          },
          {
            "agent": "Clove",
            "role": "Controller",
            "player": "Oomerz#oom",
            "matches": 5,
            "win_rate": 40.0,
            "conflict": false
          },
          {
            "agent": "Sova",
            "role": "Initiator",
            "player": "Mathman1129#1129",
            "matches": 6,
            "win_rate": 67.0,
            "conflict": false
          }
        ],
        "roles_label": "2 Controller / 2 Initiator / 1 Sentinel",
        "confidence": "High",
        "confidence_class": "pill-good",
        "conflicts": 0
      },
      {
        "map": "Pearl",
        "games": 19,
        "agents": [
          {
            "agent": "Chamber",
            "role": "Sentinel",
            "player": "balakeh#shhhh",
            "matches": 5,
            "win_rate": 20.0,
            "conflict": false
          },
          {
            "agent": "Skye",
            "role": "Initiator",
            "player": "shysoup#bruhf",
            "matches": 8,
            "win_rate": 63.0,
            "conflict": false
          },
          {
            "agent": "Omen",
            "role": "Controller",
            "player": "goblin eater#munch",
            "matches": 14,
            "win_rate": 71.0,
            "conflict": false
          },
          {
            "agent": "Sova",
            "role": "Initiator",
            "player": "Mathman1129#1129",
            "matches": 6,
            "win_rate": 67.0,
            "conflict": false
          },
          {
            "agent": "Clove",
            "role": "Controller",
            "player": "Oomerz#oom",
            "matches": 5,
            "win_rate": 40.0,
            "conflict": false
          }
        ],
        "roles_label": "2 Controller / 2 Initiator / 1 Sentinel",
        "confidence": "High",
        "confidence_class": "pill-good",
        "conflicts": 0
      },
      {
        "map": "Split",
        "games": 17,
        "agents": [
          {
            "agent": "Omen",
            "role": "Controller",
            "player": "goblin eater#munch",
            "matches": 14,
            "win_rate": 71.0,
            "conflict": false
          },
          {
            "agent": "Chamber",
            "role": "Sentinel",
            "player": "balakeh#shhhh",
            "matches": 5,
            "win_rate": 20.0,
            "conflict": false
          },
          {
            "agent": "Skye",
            "role": "Initiator",
            "player": "shysoup#bruhf",
            "matches": 8,
            "win_rate": 63.0,
            "conflict": false
          },
          {
            "agent": "Clove",
            "role": "Controller",
            "player": "Oomerz#oom",
            "matches": 5,
            "win_rate": 40.0,
            "conflict": false
          }
        ],
        "roles_label": "2 Controller / 1 Initiator / 1 Sentinel",
        "confidence": "High",
        "confidence_class": "pill-good",
        "conflicts": 0
      }
    ],
    "team_insights": [
      {
        "level": "pill-good",
        "tag": "Sample",
        "text": "Solid sample size (161 games). Trends are more trustworthy."
      },
      {
        "level": "pill-good",
        "tag": "Map Pool",
        "text": "Wide map pool (7 maps with >=5 games)."
      },
      {
        "level": "pill-mid",
        "tag": "Consistency",
        "text": "Moderate map volatility (win% stdev 11.9)."
      },
      {
        "level": "pill-bad",
        "tag": "Map Gap",
        "text": "Large win-rate gap: Corrode 68.6% vs Haven 32.0%. Expect bans into Haven."
      },
      {
        "level": "pill-good",
        "tag": "Agent Pool",
        "text": "Healthy agent diversity (top 2 = 27% of matches)."
      },
      {
        "level": "pill-mid",
        "tag": "Pocket Pick",
        "text": "Vyse wins 21.6 pts above team average on limited use (6% of matches). Consider expanding if comp fits."
      }
    ]
  },
  "insights": [
    {
      "level": "pill-good",
      "tag": "Confidence",
      "text": "Solid sample size: USC Cardinal 517 games vs BCIT Black 161. Trends are more trustworthy."
    },
    {
      "level": "pill-mid",
      "tag": "Map Pool",
      "text": "Similar map pool breadth (>=5 games): USC Cardinal 7 vs BCIT Black 7."
    },
    {
      "level": "pill-good",
      "tag": "Consistency",
      "text": "USC Cardinal is more consistent across maps (win% volatility 6.3 vs 11.9)."
    },
    {
      "level": "pill-mid",
      "tag": "Win Rate",
      "text": "BCIT Black leads on win rate (53.2% vs 55.2%)."
    },
    {
      "level": "pill-mid",
      "tag": "K/D",
      "text": "BCIT Black leads on k/d (1.06 vs 1.13)."
    },
    {
      "level": "pill-good",
      "tag": "DMG/R",
      "text": "BCIT Black leads on dmg/r (143.84 vs 144.31)."
    },
    {
      "level": "pill-good",
      "tag": "Score/R",
      "text": "USC Cardinal leads on score/r (238.85 vs 218.98)."
    },
    {
      "level": "pill-good",
      "tag": "Map Edge",
      "text": "Biggest shared-map edge: USC Cardinal on Haven (win% gap 29.2 pts; samples 67g vs 25g)."
    },
    {
      "level": "pill-good",
      "tag": "USC Cardinal Pick",
      "text": "Suggested pick: Haven (adj 60.3% vs 35.5%)."
    },
    {
      "level": "pill-bad",
      "tag": "USC Cardinal Ban",
      "text": "Suggested ban: Corrode (adj 52.3% vs 65.9%)."
    },
    {
      "level": "pill-good",
      "tag": "BCIT Black Pick",
      "text": "Suggested pick: Corrode (adj 65.9% vs 52.3%)."
    },
    {
      "level": "pill-bad",
      "tag": "BCIT Black Ban",
      "text": "Suggested ban: Haven (adj 35.5% vs 60.3%)."
    },
    {
      "level": "pill-mid",
      "tag": "Reliance",
      "text": "USC Cardinal is more top-heavy (top-2 impact share ~69% vs 43%). Target their stars to swing rounds."
    },
    {
      "level": "pill-mid",
      "tag": "Agent Meta",
      "text": "Both teams share key agent comfort picks: Sova."
    }
  ]
}